{"MAE2040": [], "MAE2300": [["PHYS1425", "APMA2120"]], "MAE3230": [], "MAE3420": [], "MAE4501": [], "MAE4513": [], "MAE4610": [], "MAE6080": [["MAE6020"]], "MAE6120": [], "MAE6270": [], "MAE6592": [], "MAE6620": [], "MAE6870": [["PHYS2415"]], "MAE6993": [], "MAE7510": [], "MAE8897": [], "MAE8999": [], "MAE9897": [], "MAE9999": [], "MAE2020": [], "MAE2030": [], "MAE2100": [["APMA1110"]], "MAE2320": [["MAE2300"]], "MAE3130": [["APMA2130"]], "MAE3210": [["APMA2130"], ["MAE2100"]], "MAE3310": [["MAE2310"]], "MAE3610": [], "MAE3710": [["MAE2320"], ["APMA2130"]], "MAE4120": [["MAE3210"]], "MAE4270": [["MAE2320"], ["CS1110", "CS1111", "CS1112"]], "MAE4511": [], "MAE4512": [], "MAE4620": [], "MAE4650": [["MAE2010", "MAE3220", "MAE3310", "MAE3610", "MAE3730"]], "MAE4690": [], "MAE4720": [], "MAE6020": [], "MAE6100": [], "MAE6594": [], "MAE8591": [], "MAE2310": [["MAE2300", "APMA2120"]], "MAE2330": [], "MAE3220": [], "MAE3820": [], "MAE3840": [], "MAE4514": [], "MAE4710": [], "MAE6250": [], "MAE6260": [], "MAE6310": [], "MAE6410": [], "MAE6430": [], "MAE6710": [["MAE6020"]], "MAE3010": [["MAE2320"]], "MAE3140": [["MAE3210"]], "MAE3620": [["MAE2000"], ["MAE3310"]], "MAE3730": [["MAE2010"], ["MAE2320"]], "MAE4260": [["MAE2320"], ["CS1110", "CS1111", "CS1112"]], "MAE4502": [], "MAE4605": [["MAE2000", "MAE3620"]], "MAE4660": [["MAE4650"]], "MAE4700": [], "MAE4730": [["MAE2320"], ["MAE3710"]], "MAE6600": [], "MAE7530": []}